dsdobjects/__init__.py
dsdobjects/base_classes.py
dsdobjects/complex_utils.py
dsdobjects/iupac_utils.py
dsdobjects/objectio.py
dsdobjects/singleton.py
dsdobjects/utils.py
dsdobjects/core/__init__.py
dsdobjects/core/deprecated.py
dsdobjects/dsdparser/__init__.py
dsdobjects/dsdparser/pil_parser.py
dsdobjects/dsdparser/seesaw_parser.py
dsdobjects/parser/__init__.py
tests/__init__.py
tests/test_base_classes.py
tests/test_complex_utils.py
tests/test_iupac_utils.py
tests/test_memory.py
tests/test_objectio.py
tests/test_utils.py
tests/dsdparser/__init__.py
tests/dsdparser/test_pil_parser.py
tests/dsdparser/test_seesaw_parser.py
dsdobjects-0.8.dist-info/LICENSE
dsdobjects-0.8.dist-info/METADATA
dsdobjects-0.8.dist-info/WHEEL
dsdobjects-0.8.dist-info/top_level.txt
dsdobjects-0.8.dist-info/RECORD
