Metadata-Version: 2.1
Name: dsdobjects
Version: 0.8
Summary: Base classes and prototype objects for DSD design
Home-page: https://github.com/DNA-and-Natural-Algorithms-Group/dsdobjects
Author: Stefan Badelt
Author-email: bad-ants-fleet@posteo.eu
Maintainer: Stefan Badelt
Maintainer-email: bad-ants-fleet@posteo.eu
License: MIT
Platform: UNKNOWN
Classifier: Development Status :: 3 - Alpha
Classifier: Programming Language :: Python :: 3.7
Classifier: Programming Language :: Python :: 3.8
Classifier: Intended Audience :: Science/Research
Requires-Python: >=3.7
Requires-Dist: pyparsing
